{
  "type": "Program",
  "body": [
    {
      "type": "ExpressionStatement",
      "expression": {
        "type": "AssignmentExpression",
        "operator": "=",
        "left": {
          "type": "MemberExpression",
          "computed": false,
          "object": {
            "type": "Identifier",
            "name": "module",
            "range": [
              840,
              846
            ],
            "loc": {
              "start": {
                "line": 24,
                "column": 0
              },
              "end": {
                "line": 24,
                "column": 6
              }
            }
          },
          "property": {
            "type": "Identifier",
            "name": "exports",
            "range": [
              847,
              854
            ],
            "loc": {
              "start": {
                "line": 24,
                "column": 7
              },
              "end": {
                "line": 24,
                "column": 14
              }
            }
          },
          "range": [
            840,
            854
          ],
          "loc": {
            "start": {
              "line": 24,
              "column": 0
            },
            "end": {
              "line": 24,
              "column": 14
            }
          }
        },
        "right": {
          "type": "FunctionExpression",
          "id": {
            "type": "Identifier",
            "name": "exports",
            "range": [
              847,
              854
            ],
            "loc": {
              "start": {
                "line": 24,
                "column": 7
              },
              "end": {
                "line": 24,
                "column": 14
              }
            }
          },
          "params": [
            {
              "type": "Identifier",
              "name": "req",
              "range": [
                866,
                869
              ],
              "loc": {
                "start": {
                  "line": 24,
                  "column": 26
                },
                "end": {
                  "line": 24,
                  "column": 29
                }
              }
            },
            {
              "type": "Identifier",
              "name": "res",
              "range": [
                871,
                874
              ],
              "loc": {
                "start": {
                  "line": 24,
                  "column": 31
                },
                "end": {
                  "line": 24,
                  "column": 34
                }
              }
            },
            {
              "type": "Identifier",
              "name": "next",
              "range": [
                876,
                880
              ],
              "loc": {
                "start": {
                  "line": 24,
                  "column": 36
                },
                "end": {
                  "line": 24,
                  "column": 40
                }
              }
            }
          ],
          "body": {
            "type": "BlockStatement",
            "body": [
              {
                "type": "ExpressionStatement",
                "expression": {
                  "type": "CallExpression",
                  "callee": {
                    "type": "CallExpression",
                    "callee": {
                      "type": "MemberExpression",
                      "computed": false,
                      "object": {
                        "type": "Identifier",
                        "name": "passport",
                        "range": [
                          913,
                          921
                        ],
                        "loc": {
                          "start": {
                            "line": 26,
                            "column": 2
                          },
                          "end": {
                            "line": 26,
                            "column": 10
                          }
                        }
                      },
                      "property": {
                        "type": "Identifier",
                        "name": "initialize",
                        "range": [
                          922,
                          932
                        ],
                        "loc": {
                          "start": {
                            "line": 26,
                            "column": 11
                          },
                          "end": {
                            "line": 26,
                            "column": 21
                          }
                        }
                      },
                      "range": [
                        913,
                        932
                      ],
                      "loc": {
                        "start": {
                          "line": 26,
                          "column": 2
                        },
                        "end": {
                          "line": 26,
                          "column": 21
                        }
                      }
                    },
                    "arguments": [],
                    "range": [
                      913,
                      934
                    ],
                    "loc": {
                      "start": {
                        "line": 26,
                        "column": 2
                      },
                      "end": {
                        "line": 26,
                        "column": 23
                      }
                    }
                  },
                  "arguments": [
                    {
                      "type": "Identifier",
                      "name": "req",
                      "range": [
                        935,
                        938
                      ],
                      "loc": {
                        "start": {
                          "line": 26,
                          "column": 24
                        },
                        "end": {
                          "line": 26,
                          "column": 27
                        }
                      }
                    },
                    {
                      "type": "Identifier",
                      "name": "res",
                      "range": [
                        940,
                        943
                      ],
                      "loc": {
                        "start": {
                          "line": 26,
                          "column": 29
                        },
                        "end": {
                          "line": 26,
                          "column": 32
                        }
                      }
                    },
                    {
                      "type": "FunctionExpression",
                      "id": null,
                      "params": [],
                      "body": {
                        "type": "BlockStatement",
                        "body": [
                          {
                            "type": "ExpressionStatement",
                            "expression": {
                              "type": "CallExpression",
                              "callee": {
                                "type": "CallExpression",
                                "callee": {
                                  "type": "MemberExpression",
                                  "computed": false,
                                  "object": {
                                    "type": "Identifier",
                                    "name": "passport",
                                    "range": [
                                      997,
                                      1005
                                    ],
                                    "loc": {
                                      "start": {
                                        "line": 28,
                                        "column": 4
                                      },
                                      "end": {
                                        "line": 28,
                                        "column": 12
                                      }
                                    }
                                  },
                                  "property": {
                                    "type": "Identifier",
                                    "name": "session",
                                    "range": [
                                      1006,
                                      1013
                                    ],
                                    "loc": {
                                      "start": {
                                        "line": 28,
                                        "column": 13
                                      },
                                      "end": {
                                        "line": 28,
                                        "column": 20
                                      }
                                    }
                                  },
                                  "range": [
                                    997,
                                    1013
                                  ],
                                  "loc": {
                                    "start": {
                                      "line": 28,
                                      "column": 4
                                    },
                                    "end": {
                                      "line": 28,
                                      "column": 20
                                    }
                                  }
                                },
                                "arguments": [],
                                "range": [
                                  997,
                                  1015
                                ],
                                "loc": {
                                  "start": {
                                    "line": 28,
                                    "column": 4
                                  },
                                  "end": {
                                    "line": 28,
                                    "column": 22
                                  }
                                }
                              },
                              "arguments": [
                                {
                                  "type": "Identifier",
                                  "name": "req",
                                  "range": [
                                    1016,
                                    1019
                                  ],
                                  "loc": {
                                    "start": {
                                      "line": 28,
                                      "column": 23
                                    },
                                    "end": {
                                      "line": 28,
                                      "column": 26
                                    }
                                  }
                                },
                                {
                                  "type": "Identifier",
                                  "name": "res",
                                  "range": [
                                    1021,
                                    1024
                                  ],
                                  "loc": {
                                    "start": {
                                      "line": 28,
                                      "column": 28
                                    },
                                    "end": {
                                      "line": 28,
                                      "column": 31
                                    }
                                  }
                                },
                                {
                                  "type": "FunctionExpression",
                                  "id": null,
                                  "params": [],
                                  "body": {
                                    "type": "BlockStatement",
                                    "body": [
                                      {
                                        "type": "ExpressionStatement",
                                        "expression": {
                                          "type": "AssignmentExpression",
                                          "operator": "=",
                                          "left": {
                                            "type": "MemberExpression",
                                            "computed": false,
                                            "object": {
                                              "type": "MemberExpression",
                                              "computed": false,
                                              "object": {
                                                "type": "Identifier",
                                                "name": "res",
                                                "range": [
                                                  1104,
                                                  1107
                                                ],
                                                "loc": {
                                                  "start": {
                                                    "line": 30,
                                                    "column": 6
                                                  },
                                                  "end": {
                                                    "line": 30,
                                                    "column": 9
                                                  }
                                                }
                                              },
                                              "property": {
                                                "type": "Identifier",
                                                "name": "locals",
                                                "range": [
                                                  1108,
                                                  1114
                                                ],
                                                "loc": {
                                                  "start": {
                                                    "line": 30,
                                                    "column": 10
                                                  },
                                                  "end": {
                                                    "line": 30,
                                                    "column": 16
                                                  }
                                                }
                                              },
                                              "range": [
                                                1104,
                                                1114
                                              ],
                                              "loc": {
                                                "start": {
                                                  "line": 30,
                                                  "column": 6
                                                },
                                                "end": {
                                                  "line": 30,
                                                  "column": 16
                                                }
                                              }
                                            },
                                            "property": {
                                              "type": "Identifier",
                                              "name": "user",
                                              "range": [
                                                1115,
                                                1119
                                              ],
                                              "loc": {
                                                "start": {
                                                  "line": 30,
                                                  "column": 17
                                                },
                                                "end": {
                                                  "line": 30,
                                                  "column": 21
                                                }
                                              }
                                            },
                                            "range": [
                                              1104,
                                              1119
                                            ],
                                            "loc": {
                                              "start": {
                                                "line": 30,
                                                "column": 6
                                              },
                                              "end": {
                                                "line": 30,
                                                "column": 21
                                              }
                                            }
                                          },
                                          "right": {
                                            "type": "MemberExpression",
                                            "computed": false,
                                            "object": {
                                              "type": "Identifier",
                                              "name": "req",
                                              "range": [
                                                1122,
                                                1125
                                              ],
                                              "loc": {
                                                "start": {
                                                  "line": 30,
                                                  "column": 24
                                                },
                                                "end": {
                                                  "line": 30,
                                                  "column": 27
                                                }
                                              }
                                            },
                                            "property": {
                                              "type": "Identifier",
                                              "name": "user",
                                              "range": [
                                                1126,
                                                1130
                                              ],
                                              "loc": {
                                                "start": {
                                                  "line": 30,
                                                  "column": 28
                                                },
                                                "end": {
                                                  "line": 30,
                                                  "column": 32
                                                }
                                              }
                                            },
                                            "range": [
                                              1122,
                                              1130
                                            ],
                                            "loc": {
                                              "start": {
                                                "line": 30,
                                                "column": 24
                                              },
                                              "end": {
                                                "line": 30,
                                                "column": 32
                                              }
                                            }
                                          },
                                          "range": [
                                            1104,
                                            1130
                                          ],
                                          "loc": {
                                            "start": {
                                              "line": 30,
                                              "column": 6
                                            },
                                            "end": {
                                              "line": 30,
                                              "column": 32
                                            }
                                          }
                                        },
                                        "range": [
                                          1104,
                                          1131
                                        ],
                                        "loc": {
                                          "start": {
                                            "line": 30,
                                            "column": 6
                                          },
                                          "end": {
                                            "line": 30,
                                            "column": 33
                                          }
                                        },
                                        "leadingComments": [
                                          {
                                            "type": "Line",
                                            "value": " Make the user available throughout the frontend",
                                            "range": [
                                              1046,
                                              1096
                                            ],
                                            "loc": {
                                              "start": {
                                                "line": 29,
                                                "column": 6
                                              },
                                              "end": {
                                                "line": 29,
                                                "column": 56
                                              }
                                            }
                                          }
                                        ]
                                      },
                                      {
                                        "type": "ExpressionStatement",
                                        "expression": {
                                          "type": "CallExpression",
                                          "callee": {
                                            "type": "Identifier",
                                            "name": "next",
                                            "range": [
                                              1141,
                                              1145
                                            ],
                                            "loc": {
                                              "start": {
                                                "line": 32,
                                                "column": 6
                                              },
                                              "end": {
                                                "line": 32,
                                                "column": 10
                                              }
                                            }
                                          },
                                          "arguments": [],
                                          "range": [
                                            1141,
                                            1147
                                          ],
                                          "loc": {
                                            "start": {
                                              "line": 32,
                                              "column": 6
                                            },
                                            "end": {
                                              "line": 32,
                                              "column": 12
                                            }
                                          }
                                        },
                                        "range": [
                                          1141,
                                          1148
                                        ],
                                        "loc": {
                                          "start": {
                                            "line": 32,
                                            "column": 6
                                          },
                                          "end": {
                                            "line": 32,
                                            "column": 13
                                          }
                                        }
                                      }
                                    ],
                                    "range": [
                                      1037,
                                      1155
                                    ],
                                    "loc": {
                                      "start": {
                                        "line": 28,
                                        "column": 44
                                      },
                                      "end": {
                                        "line": 33,
                                        "column": 5
                                      }
                                    }
                                  },
                                  "generator": false,
                                  "expression": false,
                                  "range": [
                                    1026,
                                    1155
                                  ],
                                  "loc": {
                                    "start": {
                                      "line": 28,
                                      "column": 33
                                    },
                                    "end": {
                                      "line": 33,
                                      "column": 5
                                    }
                                  }
                                }
                              ],
                              "range": [
                                997,
                                1156
                              ],
                              "loc": {
                                "start": {
                                  "line": 28,
                                  "column": 4
                                },
                                "end": {
                                  "line": 33,
                                  "column": 6
                                }
                              }
                            },
                            "range": [
                              997,
                              1157
                            ],
                            "loc": {
                              "start": {
                                "line": 28,
                                "column": 4
                              },
                              "end": {
                                "line": 33,
                                "column": 7
                              }
                            },
                            "leadingComments": [
                              {
                                "type": "Line",
                                "value": " Use the built-in sessions",
                                "range": [
                                  963,
                                  991
                                ],
                                "loc": {
                                  "start": {
                                    "line": 27,
                                    "column": 4
                                  },
                                  "end": {
                                    "line": 27,
                                    "column": 32
                                  }
                                }
                              }
                            ]
                          }
                        ],
                        "range": [
                          956,
                          1162
                        ],
                        "loc": {
                          "start": {
                            "line": 26,
                            "column": 45
                          },
                          "end": {
                            "line": 34,
                            "column": 3
                          }
                        }
                      },
                      "generator": false,
                      "expression": false,
                      "range": [
                        945,
                        1162
                      ],
                      "loc": {
                        "start": {
                          "line": 26,
                          "column": 34
                        },
                        "end": {
                          "line": 34,
                          "column": 3
                        }
                      }
                    }
                  ],
                  "range": [
                    913,
                    1163
                  ],
                  "loc": {
                    "start": {
                      "line": 26,
                      "column": 2
                    },
                    "end": {
                      "line": 34,
                      "column": 4
                    }
                  }
                },
                "range": [
                  913,
                  1164
                ],
                "loc": {
                  "start": {
                    "line": 26,
                    "column": 2
                  },
                  "end": {
                    "line": 34,
                    "column": 5
                  }
                },
                "leadingComments": [
                  {
                    "type": "Line",
                    "value": " Initialize Passport",
                    "range": [
                      887,
                      909
                    ],
                    "loc": {
                      "start": {
                        "line": 25,
                        "column": 2
                      },
                      "end": {
                        "line": 25,
                        "column": 24
                      }
                    }
                  }
                ]
              }
            ],
            "range": [
              882,
              1167
            ],
            "loc": {
              "start": {
                "line": 24,
                "column": 42
              },
              "end": {
                "line": 35,
                "column": 1
              }
            }
          },
          "generator": false,
          "expression": false,
          "range": [
            857,
            1167
          ],
          "loc": {
            "start": {
              "line": 24,
              "column": 17
            },
            "end": {
              "line": 35,
              "column": 1
            }
          }
        },
        "range": [
          840,
          1167
        ],
        "loc": {
          "start": {
            "line": 24,
            "column": 0
          },
          "end": {
            "line": 35,
            "column": 1
          }
        }
      },
      "range": [
        840,
        1168
      ],
      "loc": {
        "start": {
          "line": 24,
          "column": 0
        },
        "end": {
          "line": 35,
          "column": 2
        }
      },
      "leadingComments": [
        {
          "type": "Block",
          "value": "*\r\n * Passport Middleware\r\n *\r\n * Policy for Sails that initializes Passport.js and as well as its built-in\r\n * session support.\r\n *\r\n * In a typical web application, the credentials used to authenticate a user\r\n * will only be transmitted during the login request. If authentication\r\n * succeeds, a session will be established and maintained via a cookie set in\r\n * the user's browser.\r\n *\r\n * Each subsequent request will not contain credentials, but rather the unique\r\n * cookie that identifies the session. In order to support login sessions,\r\n * Passport will serialize and deserialize user instances to and from the\r\n * session.\r\n *\r\n * For more information on the Passport.js middleware, check out:\r\n * http://passportjs.org/guide/configure/\r\n *\r\n * @param {Object}   req\r\n * @param {Object}   res\r\n * @param {Function} next\r\n ",
          "range": [
            0,
            838
          ],
          "loc": {
            "start": {
              "line": 1,
              "column": 0
            },
            "end": {
              "line": 23,
              "column": 3
            }
          }
        }
      ]
    }
  ],
  "sourceType": "module",
  "range": [
    840,
    1168
  ],
  "loc": {
    "start": {
      "line": 24,
      "column": 0
    },
    "end": {
      "line": 35,
      "column": 2
    }
  },
  "comments": [
    {
      "type": "Block",
      "value": "*\r\n * Passport Middleware\r\n *\r\n * Policy for Sails that initializes Passport.js and as well as its built-in\r\n * session support.\r\n *\r\n * In a typical web application, the credentials used to authenticate a user\r\n * will only be transmitted during the login request. If authentication\r\n * succeeds, a session will be established and maintained via a cookie set in\r\n * the user's browser.\r\n *\r\n * Each subsequent request will not contain credentials, but rather the unique\r\n * cookie that identifies the session. In order to support login sessions,\r\n * Passport will serialize and deserialize user instances to and from the\r\n * session.\r\n *\r\n * For more information on the Passport.js middleware, check out:\r\n * http://passportjs.org/guide/configure/\r\n *\r\n * @param {Object}   req\r\n * @param {Object}   res\r\n * @param {Function} next\r\n ",
      "range": [
        0,
        838
      ],
      "loc": {
        "start": {
          "line": 1,
          "column": 0
        },
        "end": {
          "line": 23,
          "column": 3
        }
      }
    },
    {
      "type": "Line",
      "value": " Initialize Passport",
      "range": [
        887,
        909
      ],
      "loc": {
        "start": {
          "line": 25,
          "column": 2
        },
        "end": {
          "line": 25,
          "column": 24
        }
      }
    },
    {
      "type": "Line",
      "value": " Use the built-in sessions",
      "range": [
        963,
        991
      ],
      "loc": {
        "start": {
          "line": 27,
          "column": 4
        },
        "end": {
          "line": 27,
          "column": 32
        }
      }
    },
    {
      "type": "Line",
      "value": " Make the user available throughout the frontend",
      "range": [
        1046,
        1096
      ],
      "loc": {
        "start": {
          "line": 29,
          "column": 6
        },
        "end": {
          "line": 29,
          "column": 56
        }
      }
    }
  ]
}